yopmail_client/__init__.py
yopmail_client/cli.py
yopmail_client/client.py
yopmail_client/constants.py
yopmail_client/cookie_detector.py
yopmail_client/cookies.py
yopmail_client/dynamic_cookie_fetcher.py
yopmail_client/exceptions.py
yopmail_client/license_verifier.py
yopmail_client/proxy_manager.py
yopmail_client/rate_limiter.py
yopmail_client/simple_api.py
yopmail_client/utils.py
yopmail_client-1.3.2.dist-info/licenses/LICENSE
yopmail_client-1.3.2.dist-info/METADATA
yopmail_client-1.3.2.dist-info/WHEEL
yopmail_client-1.3.2.dist-info/entry_points.txt
yopmail_client-1.3.2.dist-info/top_level.txt
yopmail_client-1.3.2.dist-info/RECORD
