Metadata-Version: 2.4
Name: yopmail-client
Version: 1.3.2
Summary: A secure, licensed Python client for YOPmail disposable email service with license validation, send and RSS functionality
Home-page: https://github.com/DeGanLabs/yopmail_auto
Author: Firas Guendouz
Author-email: firasguendouz@example.com
Project-URL: Bug Reports, https://github.com/DeGanLabs/yopmail_auto/issues
Project-URL: Source, https://github.com/DeGanLabs/yopmail_auto
Project-URL: Documentation, https://github.com/DeGanLabs/yopmail_auto#readme
Classifier: Development Status :: 4 - Beta
Classifier: Intended Audience :: Developers
Classifier: License :: OSI Approved :: MIT License
Classifier: Operating System :: OS Independent
Classifier: Programming Language :: Python :: 3
Classifier: Programming Language :: Python :: 3.8
Classifier: Programming Language :: Python :: 3.9
Classifier: Programming Language :: Python :: 3.10
Classifier: Programming Language :: Python :: 3.11
Classifier: Topic :: Communications :: Email
Classifier: Topic :: Software Development :: Libraries :: Python Modules
Requires-Python: >=3.8
License-File: LICENSE
Requires-Dist: httpx>=0.24.0
Requires-Dist: beautifulsoup4>=4.12.0
Requires-Dist: python-dotenv
Provides-Extra: license
Requires-Dist: keyauth; sys_platform == "win32" and extra == "license"
Provides-Extra: dev
Requires-Dist: pytest>=7.0.0; extra == "dev"
Requires-Dist: pytest-cov>=4.0.0; extra == "dev"
Requires-Dist: pytest-mock>=3.10.0; extra == "dev"
Requires-Dist: black>=23.0.0; extra == "dev"
Requires-Dist: flake8>=6.0.0; extra == "dev"
Requires-Dist: mypy>=1.0.0; extra == "dev"
Dynamic: author
Dynamic: author-email
Dynamic: classifier
Dynamic: description
Dynamic: description-content-type
Dynamic: home-page
Dynamic: license-file
Dynamic: project-url
Dynamic: provides-extra
Dynamic: requires-dist
Dynamic: requires-python
Dynamic: summary
